<?xml version="1.0" encoding="UTF-8"?>
<MetaDataObject xmlns="http://v8.1c.ru/8.3/MDClasses" xmlns:app="http://v8.1c.ru/8.2/managed-application/core" xmlns:cfg="http://v8.1c.ru/8.1/data/enterprise/current-config" xmlns:cmi="http://v8.1c.ru/8.2/managed-application/cmi" xmlns:ent="http://v8.1c.ru/8.1/data/enterprise" xmlns:lf="http://v8.1c.ru/8.2/managed-application/logform" xmlns:style="http://v8.1c.ru/8.1/data/ui/style" xmlns:sys="http://v8.1c.ru/8.1/data/ui/fonts/system" xmlns:v8="http://v8.1c.ru/8.1/data/core" xmlns:v8ui="http://v8.1c.ru/8.1/data/ui" xmlns:web="http://v8.1c.ru/8.1/data/ui/colors/web" xmlns:win="http://v8.1c.ru/8.1/data/ui/colors/windows" xmlns:xen="http://v8.1c.ru/8.3/xcf/enums" xmlns:xpr="http://v8.1c.ru/8.3/xcf/predef" xmlns:xr="http://v8.1c.ru/8.3/xcf/readable" xmlns:xs="http://www.w3.org/2001/XMLSchema" xmlns:xsi="http://www.w3.org/2001/XMLSchema-instance" version="2.7">
	<Table uuid="eacddffc-74a6-4c72-9d9a-d0fc125c9168">
		<InternalInfo>
			<xr:GeneratedType name="ExternalDataSourceTableManager.ГалактикаБД.dbo_T_STERR" category="Manager">
				<xr:TypeId>3832ab0c-566f-4f36-b099-845401e50eae</xr:TypeId>
				<xr:ValueId>1fc6df72-ebf9-4b39-960c-e1c8b25d94ff</xr:ValueId>
			</xr:GeneratedType>
			<xr:GeneratedType name="ExternalDataSourceTableObject.ГалактикаБД.dbo_T_STERR" category="Object">
				<xr:TypeId>924efbea-d4b0-4bbb-9500-2d77d9f2e878</xr:TypeId>
				<xr:ValueId>118e5603-93c0-4c52-af6e-c6a3ca8a6d66</xr:ValueId>
			</xr:GeneratedType>
			<xr:GeneratedType name="ExternalDataSourceTableRef.ГалактикаБД.dbo_T_STERR" category="Ref">
				<xr:TypeId>60cd87cf-9ea3-44f6-9a7e-18d9fa781ef0</xr:TypeId>
				<xr:ValueId>298db196-1650-4662-8f29-77bb5ca59f04</xr:ValueId>
			</xr:GeneratedType>
			<xr:GeneratedType name="ExternalDataSourceTableList.ГалактикаБД.dbo_T_STERR" category="List">
				<xr:TypeId>a583a3d6-81c9-49dd-8e15-3ae5111fe6ce</xr:TypeId>
				<xr:ValueId>d87da016-c8f4-4ce4-be0b-070f559f9926</xr:ValueId>
			</xr:GeneratedType>
			<xr:GeneratedType name="ExternalDataSourceTableRecordSet.ГалактикаБД.dbo_T_STERR" category="RecordSet">
				<xr:TypeId>e79c3a4c-fc59-41bf-a195-9326efebb156</xr:TypeId>
				<xr:ValueId>fc35a3db-7bb7-476f-b433-a8f78f424623</xr:ValueId>
			</xr:GeneratedType>
			<xr:GeneratedType name="ExternalDataSourceTableRecordKey.ГалактикаБД.dbo_T_STERR" category="RecordKey">
				<xr:TypeId>b8d9a71d-ead7-40be-85e3-b41a4fe75cf4</xr:TypeId>
				<xr:ValueId>a6267881-ca7a-4425-a646-4feb6f3a0091</xr:ValueId>
			</xr:GeneratedType>
			<xr:GeneratedType name="ExternalDataSourceTableRecordManager.ГалактикаБД.dbo_T_STERR" category="RecordManager">
				<xr:TypeId>0c83a2bd-756a-4b02-87fb-b2d2bcd8e333</xr:TypeId>
				<xr:ValueId>581b8ede-ea1c-43b6-8c0d-0de832d279ba</xr:ValueId>
			</xr:GeneratedType>
		</InternalInfo>
		<Properties>
			<Name>dbo_T_STERR</Name>
			<Synonym/>
			<Comment/>
			<TableType>Table</TableType>
			<NameInDataSource>dbo."T$STERR"</NameInDataSource>
			<ExpressionInDataSource/>
			<TableDataType>NonobjectData</TableDataType>
			<KeyFields/>
			<PresentationField/>
			<ParentField/>
			<UnfilledParentValue xsi:nil="true"/>
			<Characteristics/>
			<UseStandardCommands>true</UseStandardCommands>
			<QuickChoice>false</QuickChoice>
			<InputByString/>
			<CreateOnInput>Auto</CreateOnInput>
			<SearchStringModeOnInputByString>Begin</SearchStringModeOnInputByString>
			<ChoiceDataGetModeOnInputByString>Directly</ChoiceDataGetModeOnInputByString>
			<ChoiceHistoryOnInput>Auto</ChoiceHistoryOnInput>
			<DefaultObjectForm/>
			<DefaultRecordForm/>
			<DefaultListForm/>
			<DefaultChoiceForm/>
			<ObjectPresentation/>
			<ExtendedObjectPresentation/>
			<RecordPresentation/>
			<ExtendedRecordPresentation/>
			<ListPresentation/>
			<ExtendedListPresentation/>
			<Explanation/>
			<IncludeHelpInContents>false</IncludeHelpInContents>
			<ReadOnly>true</ReadOnly>
			<TransactionsIsolationLevel>Auto</TransactionsIsolationLevel>
			<DataVersionField/>
			<EditType>InDialog</EditType>
			<BasedOn/>
			<DataLockFields/>
			<DataLockControlMode>Automatic</DataLockControlMode>
		</Properties>
		<ChildObjects>
			<Field uuid="8c2cf677-2944-48d8-bb05-132939d0b8d6">
				<Properties>
					<Name>Sys_UL</Name>
					<Synonym/>
					<Comment/>
					<Type>
						<v8:Type>xs:base64Binary</v8:Type>
						<v8:BinaryDataQualifiers>
							<v8:Length>8</v8:Length>
							<v8:AllowedLength>Fixed</v8:AllowedLength>
						</v8:BinaryDataQualifiers>
					</Type>
					<PasswordMode>false</PasswordMode>
					<Format/>
					<EditFormat/>
					<ToolTip/>
					<MarkNegatives>false</MarkNegatives>
					<Mask/>
					<MultiLine>false</MultiLine>
					<ExtendedEdit>false</ExtendedEdit>
					<MinValue xsi:nil="true"/>
					<MaxValue xsi:nil="true"/>
					<FillFromFillingValue>false</FillFromFillingValue>
					<FillValue xsi:nil="true"/>
					<FillChecking>DontCheck</FillChecking>
					<ChoiceParameterLinks/>
					<ChoiceParameters/>
					<QuickChoice>Auto</QuickChoice>
					<CreateOnInput>Auto</CreateOnInput>
					<ChoiceHistoryOnInput>Auto</ChoiceHistoryOnInput>
					<ChoiceForm/>
					<NameInDataSource>Sys#UL</NameInDataSource>
					<ReadOnly>false</ReadOnly>
					<AllowNull>false</AllowNull>
				</Properties>
			</Field>
			<Field uuid="56fc67df-7236-43b0-8de6-a55364866b4e">
				<Properties>
					<Name>F_NREC</Name>
					<Synonym/>
					<Comment/>
					<Type>
						<v8:Type>xs:base64Binary</v8:Type>
						<v8:BinaryDataQualifiers>
							<v8:Length>8</v8:Length>
							<v8:AllowedLength>Fixed</v8:AllowedLength>
						</v8:BinaryDataQualifiers>
					</Type>
					<PasswordMode>false</PasswordMode>
					<Format/>
					<EditFormat/>
					<ToolTip/>
					<MarkNegatives>false</MarkNegatives>
					<Mask/>
					<MultiLine>false</MultiLine>
					<ExtendedEdit>false</ExtendedEdit>
					<MinValue xsi:nil="true"/>
					<MaxValue xsi:nil="true"/>
					<FillFromFillingValue>false</FillFromFillingValue>
					<FillValue xsi:nil="true"/>
					<FillChecking>DontCheck</FillChecking>
					<ChoiceParameterLinks/>
					<ChoiceParameters/>
					<QuickChoice>Auto</QuickChoice>
					<CreateOnInput>Auto</CreateOnInput>
					<ChoiceHistoryOnInput>Auto</ChoiceHistoryOnInput>
					<ChoiceForm/>
					<NameInDataSource>F$NREC</NameInDataSource>
					<ReadOnly>false</ReadOnly>
					<AllowNull>false</AllowNull>
				</Properties>
			</Field>
			<Field uuid="0efc5f42-3c25-4d75-b23d-3f47da86a323">
				<Properties>
					<Name>F_ATL_LASTDATE</Name>
					<Synonym/>
					<Comment/>
					<Type>
						<v8:Type>xs:decimal</v8:Type>
						<v8:NumberQualifiers>
							<v8:Digits>10</v8:Digits>
							<v8:FractionDigits>0</v8:FractionDigits>
							<v8:AllowedSign>Any</v8:AllowedSign>
						</v8:NumberQualifiers>
					</Type>
					<PasswordMode>false</PasswordMode>
					<Format/>
					<EditFormat/>
					<ToolTip/>
					<MarkNegatives>false</MarkNegatives>
					<Mask/>
					<MultiLine>false</MultiLine>
					<ExtendedEdit>false</ExtendedEdit>
					<MinValue xsi:nil="true"/>
					<MaxValue xsi:nil="true"/>
					<FillFromFillingValue>false</FillFromFillingValue>
					<FillValue xsi:type="xs:decimal">0</FillValue>
					<FillChecking>DontCheck</FillChecking>
					<ChoiceParameterLinks/>
					<ChoiceParameters/>
					<QuickChoice>Auto</QuickChoice>
					<CreateOnInput>Auto</CreateOnInput>
					<ChoiceHistoryOnInput>Auto</ChoiceHistoryOnInput>
					<ChoiceForm/>
					<NameInDataSource>F$ATL_LASTDATE</NameInDataSource>
					<ReadOnly>false</ReadOnly>
					<AllowNull>false</AllowNull>
				</Properties>
			</Field>
			<Field uuid="c4509862-9e0b-4166-a471-efd2f66485dc">
				<Properties>
					<Name>F_ATL_LASTTIME</Name>
					<Synonym/>
					<Comment/>
					<Type>
						<v8:Type>xs:decimal</v8:Type>
						<v8:NumberQualifiers>
							<v8:Digits>10</v8:Digits>
							<v8:FractionDigits>0</v8:FractionDigits>
							<v8:AllowedSign>Any</v8:AllowedSign>
						</v8:NumberQualifiers>
					</Type>
					<PasswordMode>false</PasswordMode>
					<Format/>
					<EditFormat/>
					<ToolTip/>
					<MarkNegatives>false</MarkNegatives>
					<Mask/>
					<MultiLine>false</MultiLine>
					<ExtendedEdit>false</ExtendedEdit>
					<MinValue xsi:nil="true"/>
					<MaxValue xsi:nil="true"/>
					<FillFromFillingValue>false</FillFromFillingValue>
					<FillValue xsi:type="xs:decimal">0</FillValue>
					<FillChecking>DontCheck</FillChecking>
					<ChoiceParameterLinks/>
					<ChoiceParameters/>
					<QuickChoice>Auto</QuickChoice>
					<CreateOnInput>Auto</CreateOnInput>
					<ChoiceHistoryOnInput>Auto</ChoiceHistoryOnInput>
					<ChoiceForm/>
					<NameInDataSource>F$ATL_LASTTIME</NameInDataSource>
					<ReadOnly>false</ReadOnly>
					<AllowNull>false</AllowNull>
				</Properties>
			</Field>
			<Field uuid="bf7dd243-073d-4c0f-9311-040739963fa7">
				<Properties>
					<Name>F_ATL_LASTUSER</Name>
					<Synonym/>
					<Comment/>
					<Type>
						<v8:Type>xs:base64Binary</v8:Type>
						<v8:BinaryDataQualifiers>
							<v8:Length>8</v8:Length>
							<v8:AllowedLength>Fixed</v8:AllowedLength>
						</v8:BinaryDataQualifiers>
					</Type>
					<PasswordMode>false</PasswordMode>
					<Format/>
					<EditFormat/>
					<ToolTip/>
					<MarkNegatives>false</MarkNegatives>
					<Mask/>
					<MultiLine>false</MultiLine>
					<ExtendedEdit>false</ExtendedEdit>
					<MinValue xsi:nil="true"/>
					<MaxValue xsi:nil="true"/>
					<FillFromFillingValue>false</FillFromFillingValue>
					<FillValue xsi:nil="true"/>
					<FillChecking>DontCheck</FillChecking>
					<ChoiceParameterLinks/>
					<ChoiceParameters/>
					<QuickChoice>Auto</QuickChoice>
					<CreateOnInput>Auto</CreateOnInput>
					<ChoiceHistoryOnInput>Auto</ChoiceHistoryOnInput>
					<ChoiceForm/>
					<NameInDataSource>F$ATL_LASTUSER</NameInDataSource>
					<ReadOnly>false</ReadOnly>
					<AllowNull>false</AllowNull>
				</Properties>
			</Field>
			<Field uuid="bccc98bf-9bea-48b1-b59c-a7c76ebb4ebd">
				<Properties>
					<Name>F_ATL_ORIGINOFFICE</Name>
					<Synonym/>
					<Comment/>
					<Type>
						<v8:Type>xs:decimal</v8:Type>
						<v8:NumberQualifiers>
							<v8:Digits>10</v8:Digits>
							<v8:FractionDigits>0</v8:FractionDigits>
							<v8:AllowedSign>Any</v8:AllowedSign>
						</v8:NumberQualifiers>
					</Type>
					<PasswordMode>false</PasswordMode>
					<Format/>
					<EditFormat/>
					<ToolTip/>
					<MarkNegatives>false</MarkNegatives>
					<Mask/>
					<MultiLine>false</MultiLine>
					<ExtendedEdit>false</ExtendedEdit>
					<MinValue xsi:nil="true"/>
					<MaxValue xsi:nil="true"/>
					<FillFromFillingValue>false</FillFromFillingValue>
					<FillValue xsi:type="xs:decimal">0</FillValue>
					<FillChecking>DontCheck</FillChecking>
					<ChoiceParameterLinks/>
					<ChoiceParameters/>
					<QuickChoice>Auto</QuickChoice>
					<CreateOnInput>Auto</CreateOnInput>
					<ChoiceHistoryOnInput>Auto</ChoiceHistoryOnInput>
					<ChoiceForm/>
					<NameInDataSource>F$ATL_ORIGINOFFICE</NameInDataSource>
					<ReadOnly>false</ReadOnly>
					<AllowNull>false</AllowNull>
				</Properties>
			</Field>
			<Field uuid="a7e654d1-3018-4e74-a669-d2c0d0826cf8">
				<Properties>
					<Name>F_ATL_OWNER</Name>
					<Synonym/>
					<Comment/>
					<Type>
						<v8:Type>xs:base64Binary</v8:Type>
						<v8:BinaryDataQualifiers>
							<v8:Length>8</v8:Length>
							<v8:AllowedLength>Fixed</v8:AllowedLength>
						</v8:BinaryDataQualifiers>
					</Type>
					<PasswordMode>false</PasswordMode>
					<Format/>
					<EditFormat/>
					<ToolTip/>
					<MarkNegatives>false</MarkNegatives>
					<Mask/>
					<MultiLine>false</MultiLine>
					<ExtendedEdit>false</ExtendedEdit>
					<MinValue xsi:nil="true"/>
					<MaxValue xsi:nil="true"/>
					<FillFromFillingValue>false</FillFromFillingValue>
					<FillValue xsi:nil="true"/>
					<FillChecking>DontCheck</FillChecking>
					<ChoiceParameterLinks/>
					<ChoiceParameters/>
					<QuickChoice>Auto</QuickChoice>
					<CreateOnInput>Auto</CreateOnInput>
					<ChoiceHistoryOnInput>Auto</ChoiceHistoryOnInput>
					<ChoiceForm/>
					<NameInDataSource>F$ATL_OWNER</NameInDataSource>
					<ReadOnly>false</ReadOnly>
					<AllowNull>false</AllowNull>
				</Properties>
			</Field>
			<Field uuid="0d6adcbf-e71d-44bf-91c7-26912f8e9a7c">
				<Properties>
					<Name>F_ATL_BRANCH</Name>
					<Synonym/>
					<Comment/>
					<Type>
						<v8:Type>xs:base64Binary</v8:Type>
						<v8:BinaryDataQualifiers>
							<v8:Length>8</v8:Length>
							<v8:AllowedLength>Fixed</v8:AllowedLength>
						</v8:BinaryDataQualifiers>
					</Type>
					<PasswordMode>false</PasswordMode>
					<Format/>
					<EditFormat/>
					<ToolTip/>
					<MarkNegatives>false</MarkNegatives>
					<Mask/>
					<MultiLine>false</MultiLine>
					<ExtendedEdit>false</ExtendedEdit>
					<MinValue xsi:nil="true"/>
					<MaxValue xsi:nil="true"/>
					<FillFromFillingValue>false</FillFromFillingValue>
					<FillValue xsi:nil="true"/>
					<FillChecking>DontCheck</FillChecking>
					<ChoiceParameterLinks/>
					<ChoiceParameters/>
					<QuickChoice>Auto</QuickChoice>
					<CreateOnInput>Auto</CreateOnInput>
					<ChoiceHistoryOnInput>Auto</ChoiceHistoryOnInput>
					<ChoiceForm/>
					<NameInDataSource>F$ATL_BRANCH</NameInDataSource>
					<ReadOnly>false</ReadOnly>
					<AllowNull>false</AllowNull>
				</Properties>
			</Field>
			<Field uuid="891ad0df-37e0-4142-8ef3-1604f8e959c9">
				<Properties>
					<Name>F_LASTUSER</Name>
					<Synonym/>
					<Comment/>
					<Type>
						<v8:Type>xs:string</v8:Type>
						<v8:StringQualifiers>
							<v8:Length>20</v8:Length>
							<v8:AllowedLength>Variable</v8:AllowedLength>
						</v8:StringQualifiers>
					</Type>
					<PasswordMode>false</PasswordMode>
					<Format/>
					<EditFormat/>
					<ToolTip/>
					<MarkNegatives>false</MarkNegatives>
					<Mask/>
					<MultiLine>false</MultiLine>
					<ExtendedEdit>false</ExtendedEdit>
					<MinValue xsi:nil="true"/>
					<MaxValue xsi:nil="true"/>
					<FillFromFillingValue>false</FillFromFillingValue>
					<FillValue xsi:type="xs:string"/>
					<FillChecking>DontCheck</FillChecking>
					<ChoiceParameterLinks/>
					<ChoiceParameters/>
					<QuickChoice>Auto</QuickChoice>
					<CreateOnInput>Auto</CreateOnInput>
					<ChoiceHistoryOnInput>Auto</ChoiceHistoryOnInput>
					<ChoiceForm/>
					<NameInDataSource>F$LASTUSER</NameInDataSource>
					<ReadOnly>false</ReadOnly>
					<AllowNull>false</AllowNull>
				</Properties>
			</Field>
			<Field uuid="da5b4d78-249d-4e7b-bf7f-a1460cf7c3b8">
				<Properties>
					<Name>F_LASTTIME</Name>
					<Synonym/>
					<Comment/>
					<Type>
						<v8:Type>xs:decimal</v8:Type>
						<v8:NumberQualifiers>
							<v8:Digits>10</v8:Digits>
							<v8:FractionDigits>0</v8:FractionDigits>
							<v8:AllowedSign>Any</v8:AllowedSign>
						</v8:NumberQualifiers>
					</Type>
					<PasswordMode>false</PasswordMode>
					<Format/>
					<EditFormat/>
					<ToolTip/>
					<MarkNegatives>false</MarkNegatives>
					<Mask/>
					<MultiLine>false</MultiLine>
					<ExtendedEdit>false</ExtendedEdit>
					<MinValue xsi:nil="true"/>
					<MaxValue xsi:nil="true"/>
					<FillFromFillingValue>false</FillFromFillingValue>
					<FillValue xsi:type="xs:decimal">0</FillValue>
					<FillChecking>DontCheck</FillChecking>
					<ChoiceParameterLinks/>
					<ChoiceParameters/>
					<QuickChoice>Auto</QuickChoice>
					<CreateOnInput>Auto</CreateOnInput>
					<ChoiceHistoryOnInput>Auto</ChoiceHistoryOnInput>
					<ChoiceForm/>
					<NameInDataSource>F$LASTTIME</NameInDataSource>
					<ReadOnly>false</ReadOnly>
					<AllowNull>false</AllowNull>
				</Properties>
			</Field>
			<Field uuid="56291f4f-7c91-4692-ac06-129688da7811">
				<Properties>
					<Name>F_LASTDATE</Name>
					<Synonym/>
					<Comment/>
					<Type>
						<v8:Type>xs:decimal</v8:Type>
						<v8:NumberQualifiers>
							<v8:Digits>10</v8:Digits>
							<v8:FractionDigits>0</v8:FractionDigits>
							<v8:AllowedSign>Any</v8:AllowedSign>
						</v8:NumberQualifiers>
					</Type>
					<PasswordMode>false</PasswordMode>
					<Format/>
					<EditFormat/>
					<ToolTip/>
					<MarkNegatives>false</MarkNegatives>
					<Mask/>
					<MultiLine>false</MultiLine>
					<ExtendedEdit>false</ExtendedEdit>
					<MinValue xsi:nil="true"/>
					<MaxValue xsi:nil="true"/>
					<FillFromFillingValue>false</FillFromFillingValue>
					<FillValue xsi:type="xs:decimal">0</FillValue>
					<FillChecking>DontCheck</FillChecking>
					<ChoiceParameterLinks/>
					<ChoiceParameters/>
					<QuickChoice>Auto</QuickChoice>
					<CreateOnInput>Auto</CreateOnInput>
					<ChoiceHistoryOnInput>Auto</ChoiceHistoryOnInput>
					<ChoiceForm/>
					<NameInDataSource>F$LASTDATE</NameInDataSource>
					<ReadOnly>false</ReadOnly>
					<AllowNull>false</AllowNull>
				</Properties>
			</Field>
			<Field uuid="20410ad4-fd05-49e4-b7da-212139f79d31">
				<Properties>
					<Name>F_FILIALNO</Name>
					<Synonym/>
					<Comment/>
					<Type>
						<v8:Type>xs:decimal</v8:Type>
						<v8:NumberQualifiers>
							<v8:Digits>10</v8:Digits>
							<v8:FractionDigits>0</v8:FractionDigits>
							<v8:AllowedSign>Any</v8:AllowedSign>
						</v8:NumberQualifiers>
					</Type>
					<PasswordMode>false</PasswordMode>
					<Format/>
					<EditFormat/>
					<ToolTip/>
					<MarkNegatives>false</MarkNegatives>
					<Mask/>
					<MultiLine>false</MultiLine>
					<ExtendedEdit>false</ExtendedEdit>
					<MinValue xsi:nil="true"/>
					<MaxValue xsi:nil="true"/>
					<FillFromFillingValue>false</FillFromFillingValue>
					<FillValue xsi:type="xs:decimal">0</FillValue>
					<FillChecking>DontCheck</FillChecking>
					<ChoiceParameterLinks/>
					<ChoiceParameters/>
					<QuickChoice>Auto</QuickChoice>
					<CreateOnInput>Auto</CreateOnInput>
					<ChoiceHistoryOnInput>Auto</ChoiceHistoryOnInput>
					<ChoiceForm/>
					<NameInDataSource>F$FILIALNO</NameInDataSource>
					<ReadOnly>false</ReadOnly>
					<AllowNull>false</AllowNull>
				</Properties>
			</Field>
			<Field uuid="90b3be00-064e-4e4c-a2af-df8bf4b4806d">
				<Properties>
					<Name>F_CPARENT</Name>
					<Synonym/>
					<Comment/>
					<Type>
						<v8:Type>xs:base64Binary</v8:Type>
						<v8:BinaryDataQualifiers>
							<v8:Length>8</v8:Length>
							<v8:AllowedLength>Fixed</v8:AllowedLength>
						</v8:BinaryDataQualifiers>
					</Type>
					<PasswordMode>false</PasswordMode>
					<Format/>
					<EditFormat/>
					<ToolTip/>
					<MarkNegatives>false</MarkNegatives>
					<Mask/>
					<MultiLine>false</MultiLine>
					<ExtendedEdit>false</ExtendedEdit>
					<MinValue xsi:nil="true"/>
					<MaxValue xsi:nil="true"/>
					<FillFromFillingValue>false</FillFromFillingValue>
					<FillValue xsi:nil="true"/>
					<FillChecking>DontCheck</FillChecking>
					<ChoiceParameterLinks/>
					<ChoiceParameters/>
					<QuickChoice>Auto</QuickChoice>
					<CreateOnInput>Auto</CreateOnInput>
					<ChoiceHistoryOnInput>Auto</ChoiceHistoryOnInput>
					<ChoiceForm/>
					<NameInDataSource>F$CPARENT</NameInDataSource>
					<ReadOnly>false</ReadOnly>
					<AllowNull>false</AllowNull>
				</Properties>
			</Field>
			<Field uuid="a4e00633-8653-45cc-8783-f73756ff3388">
				<Properties>
					<Name>F_CCOUNTRY</Name>
					<Synonym/>
					<Comment/>
					<Type>
						<v8:Type>xs:base64Binary</v8:Type>
						<v8:BinaryDataQualifiers>
							<v8:Length>8</v8:Length>
							<v8:AllowedLength>Fixed</v8:AllowedLength>
						</v8:BinaryDataQualifiers>
					</Type>
					<PasswordMode>false</PasswordMode>
					<Format/>
					<EditFormat/>
					<ToolTip/>
					<MarkNegatives>false</MarkNegatives>
					<Mask/>
					<MultiLine>false</MultiLine>
					<ExtendedEdit>false</ExtendedEdit>
					<MinValue xsi:nil="true"/>
					<MaxValue xsi:nil="true"/>
					<FillFromFillingValue>false</FillFromFillingValue>
					<FillValue xsi:nil="true"/>
					<FillChecking>DontCheck</FillChecking>
					<ChoiceParameterLinks/>
					<ChoiceParameters/>
					<QuickChoice>Auto</QuickChoice>
					<CreateOnInput>Auto</CreateOnInput>
					<ChoiceHistoryOnInput>Auto</ChoiceHistoryOnInput>
					<ChoiceForm/>
					<NameInDataSource>F$CCOUNTRY</NameInDataSource>
					<ReadOnly>false</ReadOnly>
					<AllowNull>false</AllowNull>
				</Properties>
			</Field>
			<Field uuid="38c7c612-d098-4bc0-8c1a-471ab643c533">
				<Properties>
					<Name>F_SCODE</Name>
					<Synonym/>
					<Comment/>
					<Type>
						<v8:Type>xs:string</v8:Type>
						<v8:StringQualifiers>
							<v8:Length>20</v8:Length>
							<v8:AllowedLength>Variable</v8:AllowedLength>
						</v8:StringQualifiers>
					</Type>
					<PasswordMode>false</PasswordMode>
					<Format/>
					<EditFormat/>
					<ToolTip/>
					<MarkNegatives>false</MarkNegatives>
					<Mask/>
					<MultiLine>false</MultiLine>
					<ExtendedEdit>false</ExtendedEdit>
					<MinValue xsi:nil="true"/>
					<MaxValue xsi:nil="true"/>
					<FillFromFillingValue>false</FillFromFillingValue>
					<FillValue xsi:type="xs:string"/>
					<FillChecking>DontCheck</FillChecking>
					<ChoiceParameterLinks/>
					<ChoiceParameters/>
					<QuickChoice>Auto</QuickChoice>
					<CreateOnInput>Auto</CreateOnInput>
					<ChoiceHistoryOnInput>Auto</ChoiceHistoryOnInput>
					<ChoiceForm/>
					<NameInDataSource>F$SCODE</NameInDataSource>
					<ReadOnly>false</ReadOnly>
					<AllowNull>false</AllowNull>
				</Properties>
			</Field>
			<Field uuid="2645c688-4b84-42ec-b2f9-cbdb25a5e8e9">
				<Properties>
					<Name>F_SGNI_CODE</Name>
					<Synonym/>
					<Comment/>
					<Type>
						<v8:Type>xs:string</v8:Type>
						<v8:StringQualifiers>
							<v8:Length>20</v8:Length>
							<v8:AllowedLength>Variable</v8:AllowedLength>
						</v8:StringQualifiers>
					</Type>
					<PasswordMode>false</PasswordMode>
					<Format/>
					<EditFormat/>
					<ToolTip/>
					<MarkNegatives>false</MarkNegatives>
					<Mask/>
					<MultiLine>false</MultiLine>
					<ExtendedEdit>false</ExtendedEdit>
					<MinValue xsi:nil="true"/>
					<MaxValue xsi:nil="true"/>
					<FillFromFillingValue>false</FillFromFillingValue>
					<FillValue xsi:type="xs:string"/>
					<FillChecking>DontCheck</FillChecking>
					<ChoiceParameterLinks/>
					<ChoiceParameters/>
					<QuickChoice>Auto</QuickChoice>
					<CreateOnInput>Auto</CreateOnInput>
					<ChoiceHistoryOnInput>Auto</ChoiceHistoryOnInput>
					<ChoiceForm/>
					<NameInDataSource>F$SGNI_CODE</NameInDataSource>
					<ReadOnly>false</ReadOnly>
					<AllowNull>false</AllowNull>
				</Properties>
			</Field>
			<Field uuid="a9a10569-666e-431e-b4ca-08115dbb3014">
				<Properties>
					<Name>F_CATDATA</Name>
					<Synonym/>
					<Comment/>
					<Type>
						<v8:Type>xs:string</v8:Type>
						<v8:StringQualifiers>
							<v8:Length>20</v8:Length>
							<v8:AllowedLength>Variable</v8:AllowedLength>
						</v8:StringQualifiers>
					</Type>
					<PasswordMode>false</PasswordMode>
					<Format/>
					<EditFormat/>
					<ToolTip/>
					<MarkNegatives>false</MarkNegatives>
					<Mask/>
					<MultiLine>false</MultiLine>
					<ExtendedEdit>false</ExtendedEdit>
					<MinValue xsi:nil="true"/>
					<MaxValue xsi:nil="true"/>
					<FillFromFillingValue>false</FillFromFillingValue>
					<FillValue xsi:type="xs:string"/>
					<FillChecking>DontCheck</FillChecking>
					<ChoiceParameterLinks/>
					<ChoiceParameters/>
					<QuickChoice>Auto</QuickChoice>
					<CreateOnInput>Auto</CreateOnInput>
					<ChoiceHistoryOnInput>Auto</ChoiceHistoryOnInput>
					<ChoiceForm/>
					<NameInDataSource>F$CATDATA</NameInDataSource>
					<ReadOnly>false</ReadOnly>
					<AllowNull>false</AllowNull>
				</Properties>
			</Field>
			<Field uuid="c8e1d1f0-0f4c-4e15-982d-1116e6b0348a">
				<Properties>
					<Name>F_SNAME</Name>
					<Synonym/>
					<Comment/>
					<Type>
						<v8:Type>xs:string</v8:Type>
						<v8:StringQualifiers>
							<v8:Length>100</v8:Length>
							<v8:AllowedLength>Variable</v8:AllowedLength>
						</v8:StringQualifiers>
					</Type>
					<PasswordMode>false</PasswordMode>
					<Format/>
					<EditFormat/>
					<ToolTip/>
					<MarkNegatives>false</MarkNegatives>
					<Mask/>
					<MultiLine>false</MultiLine>
					<ExtendedEdit>false</ExtendedEdit>
					<MinValue xsi:nil="true"/>
					<MaxValue xsi:nil="true"/>
					<FillFromFillingValue>false</FillFromFillingValue>
					<FillValue xsi:type="xs:string"/>
					<FillChecking>DontCheck</FillChecking>
					<ChoiceParameterLinks/>
					<ChoiceParameters/>
					<QuickChoice>Auto</QuickChoice>
					<CreateOnInput>Auto</CreateOnInput>
					<ChoiceHistoryOnInput>Auto</ChoiceHistoryOnInput>
					<ChoiceForm/>
					<NameInDataSource>F$SNAME</NameInDataSource>
					<ReadOnly>false</ReadOnly>
					<AllowNull>false</AllowNull>
				</Properties>
			</Field>
			<Field uuid="5d49e7fc-219f-45ea-8d1a-f2bdc212f6bd">
				<Properties>
					<Name>F_CSHORTNAME</Name>
					<Synonym/>
					<Comment/>
					<Type>
						<v8:Type>xs:base64Binary</v8:Type>
						<v8:BinaryDataQualifiers>
							<v8:Length>8</v8:Length>
							<v8:AllowedLength>Fixed</v8:AllowedLength>
						</v8:BinaryDataQualifiers>
					</Type>
					<PasswordMode>false</PasswordMode>
					<Format/>
					<EditFormat/>
					<ToolTip/>
					<MarkNegatives>false</MarkNegatives>
					<Mask/>
					<MultiLine>false</MultiLine>
					<ExtendedEdit>false</ExtendedEdit>
					<MinValue xsi:nil="true"/>
					<MaxValue xsi:nil="true"/>
					<FillFromFillingValue>false</FillFromFillingValue>
					<FillValue xsi:nil="true"/>
					<FillChecking>DontCheck</FillChecking>
					<ChoiceParameterLinks/>
					<ChoiceParameters/>
					<QuickChoice>Auto</QuickChoice>
					<CreateOnInput>Auto</CreateOnInput>
					<ChoiceHistoryOnInput>Auto</ChoiceHistoryOnInput>
					<ChoiceForm/>
					<NameInDataSource>F$CSHORTNAME</NameInDataSource>
					<ReadOnly>false</ReadOnly>
					<AllowNull>false</AllowNull>
				</Properties>
			</Field>
			<Field uuid="c843a16d-6b4d-4159-ae5e-3868aea862c2">
				<Properties>
					<Name>F_WTYPE</Name>
					<Synonym/>
					<Comment/>
					<Type>
						<v8:Type>xs:decimal</v8:Type>
						<v8:NumberQualifiers>
							<v8:Digits>10</v8:Digits>
							<v8:FractionDigits>0</v8:FractionDigits>
							<v8:AllowedSign>Any</v8:AllowedSign>
						</v8:NumberQualifiers>
					</Type>
					<PasswordMode>false</PasswordMode>
					<Format/>
					<EditFormat/>
					<ToolTip/>
					<MarkNegatives>false</MarkNegatives>
					<Mask/>
					<MultiLine>false</MultiLine>
					<ExtendedEdit>false</ExtendedEdit>
					<MinValue xsi:nil="true"/>
					<MaxValue xsi:nil="true"/>
					<FillFromFillingValue>false</FillFromFillingValue>
					<FillValue xsi:type="xs:decimal">0</FillValue>
					<FillChecking>DontCheck</FillChecking>
					<ChoiceParameterLinks/>
					<ChoiceParameters/>
					<QuickChoice>Auto</QuickChoice>
					<CreateOnInput>Auto</CreateOnInput>
					<ChoiceHistoryOnInput>Auto</ChoiceHistoryOnInput>
					<ChoiceForm/>
					<NameInDataSource>F$WTYPE</NameInDataSource>
					<ReadOnly>false</ReadOnly>
					<AllowNull>false</AllowNull>
				</Properties>
			</Field>
			<Field uuid="daa29db7-ada9-4211-af30-302c96a23c36">
				<Properties>
					<Name>F_WTERR</Name>
					<Synonym/>
					<Comment/>
					<Type>
						<v8:Type>xs:decimal</v8:Type>
						<v8:NumberQualifiers>
							<v8:Digits>10</v8:Digits>
							<v8:FractionDigits>0</v8:FractionDigits>
							<v8:AllowedSign>Any</v8:AllowedSign>
						</v8:NumberQualifiers>
					</Type>
					<PasswordMode>false</PasswordMode>
					<Format/>
					<EditFormat/>
					<ToolTip/>
					<MarkNegatives>false</MarkNegatives>
					<Mask/>
					<MultiLine>false</MultiLine>
					<ExtendedEdit>false</ExtendedEdit>
					<MinValue xsi:nil="true"/>
					<MaxValue xsi:nil="true"/>
					<FillFromFillingValue>false</FillFromFillingValue>
					<FillValue xsi:type="xs:decimal">0</FillValue>
					<FillChecking>DontCheck</FillChecking>
					<ChoiceParameterLinks/>
					<ChoiceParameters/>
					<QuickChoice>Auto</QuickChoice>
					<CreateOnInput>Auto</CreateOnInput>
					<ChoiceHistoryOnInput>Auto</ChoiceHistoryOnInput>
					<ChoiceForm/>
					<NameInDataSource>F$WTERR</NameInDataSource>
					<ReadOnly>false</ReadOnly>
					<AllowNull>false</AllowNull>
				</Properties>
			</Field>
			<Field uuid="f193ecdb-ab73-4684-96e7-48a47e1cc6f9">
				<Properties>
					<Name>F_CREC</Name>
					<Synonym/>
					<Comment/>
					<Type>
						<v8:Type>xs:base64Binary</v8:Type>
						<v8:BinaryDataQualifiers>
							<v8:Length>8</v8:Length>
							<v8:AllowedLength>Fixed</v8:AllowedLength>
						</v8:BinaryDataQualifiers>
					</Type>
					<PasswordMode>false</PasswordMode>
					<Format/>
					<EditFormat/>
					<ToolTip/>
					<MarkNegatives>false</MarkNegatives>
					<Mask/>
					<MultiLine>false</MultiLine>
					<ExtendedEdit>false</ExtendedEdit>
					<MinValue xsi:nil="true"/>
					<MaxValue xsi:nil="true"/>
					<FillFromFillingValue>false</FillFromFillingValue>
					<FillValue xsi:nil="true"/>
					<FillChecking>DontCheck</FillChecking>
					<ChoiceParameterLinks/>
					<ChoiceParameters/>
					<QuickChoice>Auto</QuickChoice>
					<CreateOnInput>Auto</CreateOnInput>
					<ChoiceHistoryOnInput>Auto</ChoiceHistoryOnInput>
					<ChoiceForm/>
					<NameInDataSource>F$CREC</NameInDataSource>
					<ReadOnly>false</ReadOnly>
					<AllowNull>false</AllowNull>
				</Properties>
			</Field>
			<Field uuid="cc100aff-a13c-4bbf-9184-3c54b53fdcdf">
				<Properties>
					<Name>F_SPOSTIND</Name>
					<Synonym/>
					<Comment/>
					<Type>
						<v8:Type>xs:string</v8:Type>
						<v8:StringQualifiers>
							<v8:Length>10</v8:Length>
							<v8:AllowedLength>Variable</v8:AllowedLength>
						</v8:StringQualifiers>
					</Type>
					<PasswordMode>false</PasswordMode>
					<Format/>
					<EditFormat/>
					<ToolTip/>
					<MarkNegatives>false</MarkNegatives>
					<Mask/>
					<MultiLine>false</MultiLine>
					<ExtendedEdit>false</ExtendedEdit>
					<MinValue xsi:nil="true"/>
					<MaxValue xsi:nil="true"/>
					<FillFromFillingValue>false</FillFromFillingValue>
					<FillValue xsi:type="xs:string"/>
					<FillChecking>DontCheck</FillChecking>
					<ChoiceParameterLinks/>
					<ChoiceParameters/>
					<QuickChoice>Auto</QuickChoice>
					<CreateOnInput>Auto</CreateOnInput>
					<ChoiceHistoryOnInput>Auto</ChoiceHistoryOnInput>
					<ChoiceForm/>
					<NameInDataSource>F$SPOSTIND</NameInDataSource>
					<ReadOnly>false</ReadOnly>
					<AllowNull>false</AllowNull>
				</Properties>
			</Field>
			<Field uuid="904f24bf-d2f5-4163-975d-d9277a65e1ea">
				<Properties>
					<Name>F_DMODDATE</Name>
					<Synonym/>
					<Comment/>
					<Type>
						<v8:Type>xs:decimal</v8:Type>
						<v8:NumberQualifiers>
							<v8:Digits>10</v8:Digits>
							<v8:FractionDigits>0</v8:FractionDigits>
							<v8:AllowedSign>Any</v8:AllowedSign>
						</v8:NumberQualifiers>
					</Type>
					<PasswordMode>false</PasswordMode>
					<Format/>
					<EditFormat/>
					<ToolTip/>
					<MarkNegatives>false</MarkNegatives>
					<Mask/>
					<MultiLine>false</MultiLine>
					<ExtendedEdit>false</ExtendedEdit>
					<MinValue xsi:nil="true"/>
					<MaxValue xsi:nil="true"/>
					<FillFromFillingValue>false</FillFromFillingValue>
					<FillValue xsi:type="xs:decimal">0</FillValue>
					<FillChecking>DontCheck</FillChecking>
					<ChoiceParameterLinks/>
					<ChoiceParameters/>
					<QuickChoice>Auto</QuickChoice>
					<CreateOnInput>Auto</CreateOnInput>
					<ChoiceHistoryOnInput>Auto</ChoiceHistoryOnInput>
					<ChoiceForm/>
					<NameInDataSource>F$DMODDATE</NameInDataSource>
					<ReadOnly>false</ReadOnly>
					<AllowNull>false</AllowNull>
				</Properties>
			</Field>
			<Field uuid="74b31621-acda-49aa-8e50-019c69a6bbb6">
				<Properties>
					<Name>F_SDOPFIELD1</Name>
					<Synonym/>
					<Comment/>
					<Type>
						<v8:Type>xs:string</v8:Type>
						<v8:StringQualifiers>
							<v8:Length>50</v8:Length>
							<v8:AllowedLength>Variable</v8:AllowedLength>
						</v8:StringQualifiers>
					</Type>
					<PasswordMode>false</PasswordMode>
					<Format/>
					<EditFormat/>
					<ToolTip/>
					<MarkNegatives>false</MarkNegatives>
					<Mask/>
					<MultiLine>false</MultiLine>
					<ExtendedEdit>false</ExtendedEdit>
					<MinValue xsi:nil="true"/>
					<MaxValue xsi:nil="true"/>
					<FillFromFillingValue>false</FillFromFillingValue>
					<FillValue xsi:type="xs:string"/>
					<FillChecking>DontCheck</FillChecking>
					<ChoiceParameterLinks/>
					<ChoiceParameters/>
					<QuickChoice>Auto</QuickChoice>
					<CreateOnInput>Auto</CreateOnInput>
					<ChoiceHistoryOnInput>Auto</ChoiceHistoryOnInput>
					<ChoiceForm/>
					<NameInDataSource>F$SDOPFIELD1</NameInDataSource>
					<ReadOnly>false</ReadOnly>
					<AllowNull>false</AllowNull>
				</Properties>
			</Field>
			<Field uuid="612a1482-8b71-495b-b155-a17724ab11bb">
				<Properties>
					<Name>F_SDOPFIELD2</Name>
					<Synonym/>
					<Comment/>
					<Type>
						<v8:Type>xs:string</v8:Type>
						<v8:StringQualifiers>
							<v8:Length>50</v8:Length>
							<v8:AllowedLength>Variable</v8:AllowedLength>
						</v8:StringQualifiers>
					</Type>
					<PasswordMode>false</PasswordMode>
					<Format/>
					<EditFormat/>
					<ToolTip/>
					<MarkNegatives>false</MarkNegatives>
					<Mask/>
					<MultiLine>false</MultiLine>
					<ExtendedEdit>false</ExtendedEdit>
					<MinValue xsi:nil="true"/>
					<MaxValue xsi:nil="true"/>
					<FillFromFillingValue>false</FillFromFillingValue>
					<FillValue xsi:type="xs:string"/>
					<FillChecking>DontCheck</FillChecking>
					<ChoiceParameterLinks/>
					<ChoiceParameters/>
					<QuickChoice>Auto</QuickChoice>
					<CreateOnInput>Auto</CreateOnInput>
					<ChoiceHistoryOnInput>Auto</ChoiceHistoryOnInput>
					<ChoiceForm/>
					<NameInDataSource>F$SDOPFIELD2</NameInDataSource>
					<ReadOnly>false</ReadOnly>
					<AllowNull>false</AllowNull>
				</Properties>
			</Field>
			<Field uuid="28283e04-d756-4777-a94b-3d701300d8e2">
				<Properties>
					<Name>F_CDOPFIELD1</Name>
					<Synonym/>
					<Comment/>
					<Type>
						<v8:Type>xs:base64Binary</v8:Type>
						<v8:BinaryDataQualifiers>
							<v8:Length>8</v8:Length>
							<v8:AllowedLength>Fixed</v8:AllowedLength>
						</v8:BinaryDataQualifiers>
					</Type>
					<PasswordMode>false</PasswordMode>
					<Format/>
					<EditFormat/>
					<ToolTip/>
					<MarkNegatives>false</MarkNegatives>
					<Mask/>
					<MultiLine>false</MultiLine>
					<ExtendedEdit>false</ExtendedEdit>
					<MinValue xsi:nil="true"/>
					<MaxValue xsi:nil="true"/>
					<FillFromFillingValue>false</FillFromFillingValue>
					<FillValue xsi:nil="true"/>
					<FillChecking>DontCheck</FillChecking>
					<ChoiceParameterLinks/>
					<ChoiceParameters/>
					<QuickChoice>Auto</QuickChoice>
					<CreateOnInput>Auto</CreateOnInput>
					<ChoiceHistoryOnInput>Auto</ChoiceHistoryOnInput>
					<ChoiceForm/>
					<NameInDataSource>F$CDOPFIELD1</NameInDataSource>
					<ReadOnly>false</ReadOnly>
					<AllowNull>false</AllowNull>
				</Properties>
			</Field>
			<Field uuid="e200e57a-4c81-4f12-b4eb-61f6a8dc369c">
				<Properties>
					<Name>F_CDOPFIELD2</Name>
					<Synonym/>
					<Comment/>
					<Type>
						<v8:Type>xs:base64Binary</v8:Type>
						<v8:BinaryDataQualifiers>
							<v8:Length>8</v8:Length>
							<v8:AllowedLength>Fixed</v8:AllowedLength>
						</v8:BinaryDataQualifiers>
					</Type>
					<PasswordMode>false</PasswordMode>
					<Format/>
					<EditFormat/>
					<ToolTip/>
					<MarkNegatives>false</MarkNegatives>
					<Mask/>
					<MultiLine>false</MultiLine>
					<ExtendedEdit>false</ExtendedEdit>
					<MinValue xsi:nil="true"/>
					<MaxValue xsi:nil="true"/>
					<FillFromFillingValue>false</FillFromFillingValue>
					<FillValue xsi:nil="true"/>
					<FillChecking>DontCheck</FillChecking>
					<ChoiceParameterLinks/>
					<ChoiceParameters/>
					<QuickChoice>Auto</QuickChoice>
					<CreateOnInput>Auto</CreateOnInput>
					<ChoiceHistoryOnInput>Auto</ChoiceHistoryOnInput>
					<ChoiceForm/>
					<NameInDataSource>F$CDOPFIELD2</NameInDataSource>
					<ReadOnly>false</ReadOnly>
					<AllowNull>false</AllowNull>
				</Properties>
			</Field>
			<Field uuid="68936eab-bf5a-4193-983a-e8d5c78b36e0">
				<Properties>
					<Name>F_SYSCODE</Name>
					<Synonym/>
					<Comment/>
					<Type>
						<v8:Type>xs:decimal</v8:Type>
						<v8:NumberQualifiers>
							<v8:Digits>5</v8:Digits>
							<v8:FractionDigits>0</v8:FractionDigits>
							<v8:AllowedSign>Any</v8:AllowedSign>
						</v8:NumberQualifiers>
					</Type>
					<PasswordMode>false</PasswordMode>
					<Format/>
					<EditFormat/>
					<ToolTip/>
					<MarkNegatives>false</MarkNegatives>
					<Mask/>
					<MultiLine>false</MultiLine>
					<ExtendedEdit>false</ExtendedEdit>
					<MinValue xsi:nil="true"/>
					<MaxValue xsi:nil="true"/>
					<FillFromFillingValue>false</FillFromFillingValue>
					<FillValue xsi:type="xs:decimal">0</FillValue>
					<FillChecking>DontCheck</FillChecking>
					<ChoiceParameterLinks/>
					<ChoiceParameters/>
					<QuickChoice>Auto</QuickChoice>
					<CreateOnInput>Auto</CreateOnInput>
					<ChoiceHistoryOnInput>Auto</ChoiceHistoryOnInput>
					<ChoiceForm/>
					<NameInDataSource>F$SYSCODE</NameInDataSource>
					<ReadOnly>false</ReadOnly>
					<AllowNull>false</AllowNull>
				</Properties>
			</Field>
			<Field uuid="86ea7e1a-1e68-4cc5-97d4-2f92a6e54dc3">
				<Properties>
					<Name>F_DOPSTR</Name>
					<Synonym/>
					<Comment/>
					<Type>
						<v8:Type>xs:string</v8:Type>
						<v8:StringQualifiers>
							<v8:Length>200</v8:Length>
							<v8:AllowedLength>Variable</v8:AllowedLength>
						</v8:StringQualifiers>
					</Type>
					<PasswordMode>false</PasswordMode>
					<Format/>
					<EditFormat/>
					<ToolTip/>
					<MarkNegatives>false</MarkNegatives>
					<Mask/>
					<MultiLine>false</MultiLine>
					<ExtendedEdit>false</ExtendedEdit>
					<MinValue xsi:nil="true"/>
					<MaxValue xsi:nil="true"/>
					<FillFromFillingValue>false</FillFromFillingValue>
					<FillValue xsi:type="xs:string"/>
					<FillChecking>DontCheck</FillChecking>
					<ChoiceParameterLinks/>
					<ChoiceParameters/>
					<QuickChoice>Auto</QuickChoice>
					<CreateOnInput>Auto</CreateOnInput>
					<ChoiceHistoryOnInput>Auto</ChoiceHistoryOnInput>
					<ChoiceForm/>
					<NameInDataSource>F$DOPSTR</NameInDataSource>
					<ReadOnly>false</ReadOnly>
					<AllowNull>false</AllowNull>
				</Properties>
			</Field>
		</ChildObjects>
	</Table>
</MetaDataObject>